Metadata-Version: 2.4
Name: dna_features_viewer
Version: 3.1.4
Summary: Plot features from DNA sequences (e.g. Genbank) with Python
Home-page: https://github.com/Edinburgh-Genome-Foundry/DnaFeaturesViewer
Author: Zulko
License-Expression: MIT
Project-URL: Homepage, https://github.com/Edinburgh-Genome-Foundry/DnaFeaturesViewer
Keywords: DNA,Sequence,Feature,Genbank,Biopython,Matplotlib
License-File: LICENCE.txt
Requires-Dist: matplotlib>=3
Requires-Dist: Biopython
Requires-Dist: packaging
Dynamic: home-page
Dynamic: license-file
